video_utils/__init__.py
video_utils/codec.py
video_utils/colour.py
video_utils/fileMap.py
video_utils/parse_episode.py
video_utils/validators.py
video_utils/video.py
video_utils-2.5.1.dist-info/METADATA
video_utils-2.5.1.dist-info/WHEEL
video_utils-2.5.1.dist-info/licenses/LICENSE.md
video_utils-2.5.1.dist-info/RECORD
