Metadata-Version: 2.4
Name: video_utils
Version: 2.5.1
Summary: This library provides utilities for dealing folders full of video files, including parsing out all metadata and intelligent caching.
Author-email: Justin Dray <justin@dray.be>
License-Expression: MIT
License-File: LICENSE.md
Requires-Python: <4,>=3.12.0
Requires-Dist: colorama<0.5,>=0.4.6
Requires-Dist: iso639>=0.1.4
Requires-Dist: pymediainfo<8,>=7.0.0
Requires-Dist: rich<15,>=13.0.0
